ossuary/__init__.py
ossuary/__main__.py
ossuary/_version.py
ossuary/color.py
ossuary/draw.py
ossuary/hammer.py
ossuary/pmf.py
ossuary/roll.py
ossuary-0.1.0a0.dist-info/METADATA
ossuary-0.1.0a0.dist-info/WHEEL
ossuary-0.1.0a0.dist-info/entry_points.txt
ossuary-0.1.0a0.dist-info/licenses/LICENSE.md
ossuary-0.1.0a0.dist-info/RECORD
