Metadata-Version: 2.1
Name: ossuary
Version: 0.1.0a0
Summary: dice analysis toolkit
Project-URL: Homepage, https://github.com/bszonye/ossuary
Project-URL: Repository, https://github.com/bszonye/ossuary
Project-URL: Documentation, https://github.com/bszonye/ossuary
Author-email: Bradd Szonye <bszonye@gmail.com>
License: MIT
License-File: LICENSE.md
Keywords: dice,probability
Classifier: Development Status :: 3 - Alpha
Classifier: Programming Language :: Python
Classifier: Programming Language :: Python :: 3.11
Requires-Python: >=3.11.0rc2
Provides-Extra: gtkplot
Requires-Dist: ossuary[plot]; extra == 'gtkplot'
Requires-Dist: pygobject; extra == 'gtkplot'
Provides-Extra: plot
Requires-Dist: matplotlib; extra == 'plot'
